apachelabs/__init__.py
apachelabs/apachelm.py
apacheapi-0.3.0.dist-info/METADATA
apacheapi-0.3.0.dist-info/WHEEL
apacheapi-0.3.0.dist-info/licenses/LICENSE
apacheapi-0.3.0.dist-info/RECORD
