Metadata-Version: 2.3
Name: apacheapi
Version: 0.3.0
Summary: A simplified wrapper for Mistral AI API/Hugging Face so that developers can easily work with Apache Lab Models.
Project-URL: Homepage, https://github.com/Apache-Labs
Project-URL: Bug Tracker, https://github.com/Apache-Labs
Author-email: Apache Labs <apachemllabs@gmail.com>
License-File: LICENSE
Classifier: License :: OSI Approved :: MIT License
Classifier: Operating System :: OS Independent
Classifier: Programming Language :: Python :: 3
Requires-Python: >=3.7
Requires-Dist: mistralai
